requests_chain/__init__.py
requests_chain/chained_socks.py
requests_chain/requests_patched.py
requests_chain-0.1.2.dist-info/LICENSE
requests_chain-0.1.2.dist-info/METADATA
requests_chain-0.1.2.dist-info/WHEEL
requests_chain-0.1.2.dist-info/top_level.txt
requests_chain-0.1.2.dist-info/RECORD
