Metadata-Version: 2.1
Name: requests-chain
Version: 0.1.2
Summary: Adds the ability of using a proxy chains to the python requests module. 
Author-email: makovez <namosoermejo@gmail.com>
License: MIT License
License-File: LICENSE
Requires-Dist: requests
Requires-Dist: six
